setup.py
uaioftp.py
micropython_uaioftp.egg-info/PKG-INFO
micropython_uaioftp.egg-info/SOURCES.txt
micropython_uaioftp.egg-info/dependency_links.txt
micropython_uaioftp.egg-info/pbr.json
micropython_uaioftp.egg-info/requires.txt
micropython_uaioftp.egg-info/top_level.txt