Metadata-Version: 1.0
Name: micropython-uaioftp
Version: 0.9.2
Summary: Lightweight ftp asyncio library for MicroPython.
Home-page: https://github.com/cwyark/micropython-uaioftp
Author: Chester
Author-email: cwyark@gmail.com
License: MIT
Platform: UNKNOWN
